hashfs/__init__.py
hashfs/__meta__.py
hashfs/_compat.py
hashfs/hashfs.py
hashfs/utils.py
hashfs2-1.1.0.dist-info/AUTHORS.rst
hashfs2-1.1.0.dist-info/LICENSE.rst
hashfs2-1.1.0.dist-info/METADATA
hashfs2-1.1.0.dist-info/WHEEL
hashfs2-1.1.0.dist-info/top_level.txt
hashfs2-1.1.0.dist-info/RECORD
