Metadata-Version: 2.1
Name: hashfs2
Version: 1.1.0
Summary: A content-addressable file management system.
Home-page: https://github.com/ramwin/hashfs
Author: Derrick Gilland
Author-email: dgilland@gmail.com
License: MIT License
Keywords: hashfs hash file system content addressable fixed storage
Classifier: Development Status :: 3 - Alpha
Classifier: Intended Audience :: Developers
Classifier: Operating System :: OS Independent
Classifier: Programming Language :: Python
Classifier: License :: OSI Approved :: MIT License
Classifier: Topic :: Software Development :: Libraries
Classifier: Topic :: Software Development :: Libraries :: Python Modules
Classifier: Topic :: System :: Filesystems
Classifier: Programming Language :: Python
Classifier: Programming Language :: Python :: 2
Classifier: Programming Language :: Python :: 2.7
Classifier: Programming Language :: Python :: 3
Classifier: Programming Language :: Python :: 3.4
Classifier: Programming Language :: Python :: 3.5
Classifier: Programming Language :: Python :: 3.6
Classifier: Programming Language :: Python :: 3.7
License-File: LICENSE.rst
License-File: AUTHORS.rst
